latzero/__init__.py
latzero/py.typed
latzero/async_api/__init__.py
latzero/async_api/pool.py
latzero/cli/__init__.py
latzero/cli/main.py
latzero/core/__init__.py
latzero/core/cleanup.py
latzero/core/encryption.py
latzero/core/events.py
latzero/core/events_metrics.py
latzero/core/events_types.py
latzero/core/locking.py
latzero/core/memory.py
latzero/core/pool.py
latzero/core/registry.py
latzero/examples/encrypted_pool.py
latzero/examples/events_demo.py
latzero/examples/multi_client_demo.py
latzero/examples/simple_pool.py
latzero/persistence/__init__.py
latzero/persistence/snapshot.py
latzero/utils/__init__.py
latzero/utils/exceptions.py
latzero/utils/logging.py
latzero/utils/serializer.py
latzero/utils/type_checker.py
latzero-0.3.1.dist-info/licenses/LICENSE
latzero-0.3.1.dist-info/METADATA
latzero-0.3.1.dist-info/WHEEL
latzero-0.3.1.dist-info/entry_points.txt
latzero-0.3.1.dist-info/top_level.txt
latzero-0.3.1.dist-info/RECORD
