Metadata-Version: 2.4
Name: latzero
Version: 0.3.1
Summary: Zero-latency, zero-fuss shared memory for Python — dynamic, encrypted, and insanely fast.
Home-page: https://github.com/Latency-Zero/python-client
Author: BRAHMAI
Author-email: BRAHMAI <hello@brahmai.in>
License: MIT
Project-URL: Homepage, https://github.com/Latency-Zero/python-client
Project-URL: Documentation, https://github.com/Latency-Zero/python-client#readme
Project-URL: Repository, https://github.com/Latency-Zero/python-client.git
Project-URL: Issues, https://github.com/Latency-Zero/python-client/issues
Keywords: ipc,shared-memory,inter-process-communication,memory,cache,fast,zero-latency,encryption
Classifier: Development Status :: 4 - Beta
Classifier: Intended Audience :: Developers
Classifier: License :: OSI Approved :: MIT License
Classifier: Operating System :: OS Independent
Classifier: Programming Language :: Python :: 3
Classifier: Programming Language :: Python :: 3.8
Classifier: Programming Language :: Python :: 3.9
Classifier: Programming Language :: Python :: 3.10
Classifier: Programming Language :: Python :: 3.11
Classifier: Programming Language :: Python :: 3.12
Classifier: Topic :: Software Development :: Libraries :: Python Modules
Classifier: Topic :: System :: Distributed Computing
Requires-Python: >=3.8
License-File: LICENSE
Requires-Dist: cryptography>=3.4
Requires-Dist: psutil>=5.8
Provides-Extra: fast
Requires-Dist: msgpack>=1.0; extra == "fast"
Provides-Extra: dev
Requires-Dist: pytest>=7.0; extra == "dev"
Requires-Dist: pytest-asyncio>=0.20; extra == "dev"
Requires-Dist: pytest-cov>=4.0; extra == "dev"
Requires-Dist: mypy>=1.0; extra == "dev"
Requires-Dist: ruff>=0.1; extra == "dev"
Requires-Dist: build; extra == "dev"
Requires-Dist: twine; extra == "dev"
Dynamic: author
Dynamic: home-page
Dynamic: license-file
Dynamic: requires-python
